template_formatter/AppContext.py
template_formatter/FStringFormatter.py
template_formatter/ITemplateFormatter.py
template_formatter/Jinja2Formatter.py
template_formatter/Jinja2Model.py
template_formatter/PythonFormatFormatter.py
template_formatter/PythonFormatter.py
template_formatter/__init__.py
template_formatter/main.py
template_formatter/version.py
template_formatter-1.4.0.dist-info/LICENSE.md
template_formatter-1.4.0.dist-info/METADATA
template_formatter-1.4.0.dist-info/WHEEL
template_formatter-1.4.0.dist-info/entry_points.txt
template_formatter-1.4.0.dist-info/top_level.txt
template_formatter-1.4.0.dist-info/RECORD
