Metadata-Version: 2.1
Name: template-formatter
Version: 1.4.0
Summary: Wrapper to jinja2 template system
Home-page: https://github.com/Koldar/template-formatter.git
Author: Massimo Bono
Author-email: massimobono1@gmail.com
License: UNKNOWN
Platform: UNKNOWN
Classifier: Programming Language :: Python :: 3
Classifier: License :: OSI Approved :: Apache Software License
Classifier: Operating System :: OS Independent
Requires-Python: >=3.8
Requires-Dist: altgraph
Requires-Dist: future
Requires-Dist: Jinja2
Requires-Dist: MarkupSafe
Requires-Dist: pefile
Requires-Dist: pywin32-ctypes
Requires-Dist: semver
Requires-Dist: toml
